MathHelper/__init__.py
math_helper-0.1.4.dist-info/licenses/LICENSE
math_helper-0.1.4.dist-info/METADATA
math_helper-0.1.4.dist-info/WHEEL
math_helper-0.1.4.dist-info/top_level.txt
math_helper-0.1.4.dist-info/RECORD
